keeper_cnab240/__init__.py
keeper_cnab240/attribute.py
keeper_cnab240/company.py
keeper_cnab240/file.py
keeper_cnab240/file_section.py
keeper_cnab240/payment.py
keeper_cnab240/payment_status.py
keeper_cnab240/segment_section.py
keeper_cnab240/banks/__init__.py
keeper_cnab240/banks/bank.py
keeper_cnab240/banks/bank_account.py
keeper_cnab240/banks/Itau/Itau.py
keeper_cnab240/banks/Itau/__init__.py
keeper_cnab240/banks/Itau/file_footer.py
keeper_cnab240/banks/Itau/file_header.py
keeper_cnab240/banks/Itau/payment_methods.py
keeper_cnab240/banks/Itau/payment_status.py
keeper_cnab240/banks/Itau/payment_types.py
keeper_cnab240/banks/Itau/segments/A.py
keeper_cnab240/banks/Itau/segments/ANF.py
keeper_cnab240/banks/Itau/segments/J.py
keeper_cnab240/banks/Itau/segments/J52.py
keeper_cnab240/banks/Itau/segments/__init__.py
keeper_cnab240/banks/Itau/segments/footers/__init__.py
keeper_cnab240/banks/Itau/segments/footers/slip_footer.py
keeper_cnab240/banks/Itau/segments/footers/transfer_footer.py
keeper_cnab240/banks/Itau/segments/headers/__init__.py
keeper_cnab240/banks/Itau/segments/headers/slip_header.py
keeper_cnab240/banks/Itau/segments/headers/transfer_header.py
keeper_cnab240/exceptions/InvalidPaymentMethod.py
keeper_cnab240/exceptions/__init__.py
keeper_cnab240-0.0b5.dist-info/LICENSE
keeper_cnab240-0.0b5.dist-info/METADATA
keeper_cnab240-0.0b5.dist-info/WHEEL
keeper_cnab240-0.0b5.dist-info/top_level.txt
keeper_cnab240-0.0b5.dist-info/RECORD
