Metadata-Version: 2.1
Name: keeper-cnab240
Version: 0.0b5
Summary: A CNAB 240 Package to process Bank payment shipping files and return files.
Home-page: https://github.com/KeeperFormaturas/cnab240
Author: Keeper Formaturas
Author-email: ola@keeperformaturas.com.br
License: UNKNOWN
Platform: UNKNOWN
Classifier: Programming Language :: Python :: 3
Classifier: License :: OSI Approved :: MIT License
Classifier: Operating System :: OS Independent
